{"name":"FloatBar Plugin v1.2","tagline":"基于jQuery的浮动边栏插件","body":"用于控制页面主体以外的容器定位插件，分左上，左下，右上，右下四个方位排布。\r\n\r\n兼容IE6浏览器\r\n\r\n更正参数middle为vertical;\r\n简化页面布局复杂性。\r\n\r\ndemo.html可能没有及时更正，使用时请查看参数是否传对\r\n\r\n```js\r\n\tliveHeight:360,                       // 活动高度: 取0时边栏位置为固定样式\r\n\tbodyWidth:960,                        // 页面布局宽度\r\n\twinMinHeight:600,                     // 浏览器最小高度\r\n\ttopFixHeight:30,                      // 顶部Fixed层的高度 vertical:top共用\r\n\tspaceWidth:10,                        // 浮动边栏与页面的间距\r\n\talign:\"right\",                        // 浮动边栏左右停靠方式：right | left\r\n\tvertical:\"bottom\",                    // 浮动边栏上下停靠方式：bottom | top\r\n\tspeed:300,                            // 速度：非0毫秒数值 | \"slow\" | \"fast\"\r\n\taniOnOff:true,                        // 效果开关：true | false\r\n\tmoveOnOff:true                        // 运动开关：true | false\r\n```\r\n\r\n\r\n**使用方法**\r\n```js\r\n\t$(element).floatBar();\r\n\t// 浮动边栏默认右下方\r\n\t\r\n\t$(element).floatBar({\r\n\tvertical:\"top\"\r\n\t});\r\n\t// 右上方 可以追加设置topFixHeight的值\r\n\t\r\n\t$(element).floatBar({\r\n\tvertical:\"top\",\r\n\talign:\"left\"\r\n\t});\r\n\t// 左上方 可以追加设置topFixHeight的值\r\n\t\r\n\t$(element).floatBar({\r\n\talign:\"left\"\r\n\t});\r\n\t// 左下方\r\n```\r\n\r\n**CSS写法**\r\n```css\r\n\t/* 上方（包含左上方和右上方） */\r\n\telement{top:value;}\r\n\tchildelement{width:value;height:value;...}\r\n\t\r\n\t/* 下方（包含左下方和右下方） */\r\n\telement{bottom:value}\r\n\tchildelement{width:value;height:value;...}\r\n\t\r\n\t/* 兼容IE6浏览器写法*/\r\n\t*html element{margin-top:value;}         /* 上方（包含左上方和右上方） */\r\n\t*html element{margin-top:-value;}        /* 下方（包含左下方和右下方） */\r\n```\r\n\r\n**HTML写法**\r\n```html\r\n\t<div class=\"element\">\r\n\t\t<div class=\"childelement\"></div>\r\n\t</div>\r\n```\r\n===============================================================================\r\n\r\n*增加参数*\r\n```js\r\n\teleFocus:\"focus\",                     // 焦点：class=\"focus\"\r\n\teleName:\"back\",                       // 元素名称\r\n\teleLabel:\"li\",                        // 结构标签\r\n\tanchorIndex:\"anchor-index\",           // 锚节点\r\n\teleMargin:10,                         // 板块间距\r\n\tmouseCtrl:\"click\",                    // 鼠标事件：click | mouseover\r\n\tfocusOnOff:true                       // 滚动获焦开关：false | true\r\n```\r\n\r\n*增加锚节点*\r\n```html\r\n\t<div anchor-index=\"1\">...</div>\r\n\t<div anchor-index=\"2\">...</div>\r\n\t...\r\n\t<!-- anchor-index可自定义 -->\r\n\t<!-- 传值 -> anchorIndex:\"自定义\" -->\r\n\t<!-- 如：<div aaa=\"1\">...</div> -->\r\n\t<!-- 传值 -> anchorIndex:\"aaa\" -->\r\n```\r\n\r\n*增加滚动获焦功能*\r\n```html\r\n\t<!-- 默认结构 -->\r\n\t<div>\r\n\t\t<ul>\r\n\t\t\t<li class=\"focus\">...</li>\r\n\t\t\t<li>...</li>\r\n\t\t\t...\r\n\t\t</ul>\r\n\t</div>\r\n\t<!-- 标签 && 类 可自定义 -->\r\n\t<!-- 传值 -> eleLabel:\"自定义\" -->\r\n\t<!-- 传值 -> eleFocus:\"自定义\" -->\r\n\t<div>\r\n\t\t<a class=\"bar\" href=\"javascript:;\">...</a>\r\n\t\t<a href=\"javascript:;\">...</a>\r\n\t\t...\r\n\t</div>\r\n\t<!-- 如：eleLabel:\"a\" -->\r\n\t<!-- 如：eleFocus:\"bar\" -->\r\n```\r\n\r\n*增加获焦关闭功能(焦点不可见)*\r\n```js\r\n\tfocusOnOff:false\r\n```\r\n\r\n*增加置顶置底功能*\r\n```html\r\n\t<a href=\"javascript:;\" class=\"backtop\">返回顶部</a>\r\n\t<a href=\"javascript:;\" class=\"backbottom\">去底部</a>\r\n\t<!-- 标签可自定义 -->\r\n\t<!-- class需遵循规则 -> 自定义+top || 自定义+bottom -->\r\n\t<!-- 传值 -> eleName:\"自定义\" -->\r\n```\r\n\r\n\r\n\r\n\r\n","google":"","note":"Don't delete this file! It's used internally to help with page regeneration."}